setup.py
digTokenizerExtractor/__init__.py
digTokenizerExtractor/tokenizer_extractor.py
digTokenizerExtractor.egg-info/PKG-INFO
digTokenizerExtractor.egg-info/SOURCES.txt
digTokenizerExtractor.egg-info/dependency_links.txt
digTokenizerExtractor.egg-info/requires.txt
digTokenizerExtractor.egg-info/top_level.txt
test/test_token_extractor.py