Metadata-Version: 1.1
Name: digTokenizerExtractor
Version: 0.3.1
Summary: digTokenizerExtractor
Home-page: https://github.com/usc-isi-i2/dig-tokenizer-extractor
Author: Jason Slepicka
Author-email: jasonslepicka@gmail.com
License: UNKNOWN
Download-URL: https://github.com/usc-isi-i2/dig-tokenizer-extractor
Platform: UNKNOWN
